LICENSE
MANIFEST.in
README.md
setup.py
django_polls.egg-info/PKG-INFO
django_polls.egg-info/SOURCES.txt
django_polls.egg-info/dependency_links.txt
django_polls.egg-info/requires.txt
django_polls.egg-info/top_level.txt
polls/__init__.py
polls/admin.py
polls/models.py
polls/urls.py
polls/views.py
polls/migrations/0001_initial.py
polls/migrations/0002_auto__add_vote__add_field_poll_description.py
polls/migrations/0003_auto__add_unique_vote_poll_user.py
polls/migrations/__init__.py
polls/templates/polls/poll_detail.html
polls/templates/polls/poll_list.html
tests/__init__.py
tests/models.py
tests/settings.py
tests/test_models.py