Metadata-Version: 1.0
Name: django-polls
Version: 0.2.1
Summary: A simple polls app for django
Home-page: https://github.com/byteweaver/django-polls
Author: noxan
Author-email: contact@byteweaver.net
License: MIT License
Platform: UNKNOWN
